pyfx/__init__.py
pyfx/__version__.py
pyfx/app.py
pyfx/cli.py
pyfx/cli_utils.py
pyfx/error.py
pyfx/config/__init__.py
pyfx/config/config.py
pyfx/config/config_parser.py
pyfx/config/yaml/__init__.py
pyfx/config/yaml/config.yml
pyfx/config/yaml/config_schema.yml
pyfx/config/yaml/keymaps/__init__.py
pyfx/config/yaml/keymaps/basic.yml
pyfx/config/yaml/keymaps/emacs.yml
pyfx/config/yaml/keymaps/vim.yml
pyfx/config/yaml/themes/__init__.py
pyfx/config/yaml/themes/basic.yml
pyfx/model/__init__.py
pyfx/model/model.py
pyfx/model/autocomplete/__init__.py
pyfx/model/autocomplete/autocomplete_listener.py
pyfx/model/common/__init__.py
pyfx/model/common/jsonpath/JSONPath.g4
pyfx/model/common/jsonpath/JSONPath.interp
pyfx/model/common/jsonpath/JSONPath.tokens
pyfx/model/common/jsonpath/JSONPathLexer.interp
pyfx/model/common/jsonpath/JSONPathLexer.py
pyfx/model/common/jsonpath/JSONPathLexer.tokens
pyfx/model/common/jsonpath/JSONPathListener.py
pyfx/model/common/jsonpath/JSONPathParser.py
pyfx/model/common/jsonpath/__init__.py
pyfx/service/__init__.py
pyfx/service/client.py
pyfx/service/dispatcher.py
pyfx/view/__init__.py
pyfx/view/keys.py
pyfx/view/themes.py
pyfx/view/view_frame.py
pyfx/view/view_manager.py
pyfx/view/view_mediator.py
pyfx/view/common/__init__.py
pyfx/view/common/frame.py
pyfx/view/common/popup.py
pyfx/view/common/selectable_text.py
pyfx/view/components/__init__.py
pyfx/view/components/abstract_component_keys.py
pyfx/view/components/autocomplete_popup.py
pyfx/view/components/help_popup.py
pyfx/view/components/json_browser.py
pyfx/view/components/query_bar.py
pyfx/view/components/warning_bar.py
pyfx/view/json_lib/__init__.py
pyfx/view/json_lib/json_composite_end_node.py
pyfx/view/json_lib/json_composite_node.py
pyfx/view/json_lib/json_listbox.py
pyfx/view/json_lib/json_listwalker.py
pyfx/view/json_lib/json_node_creator.py
pyfx/view/json_lib/json_node_factory.py
pyfx/view/json_lib/json_simple_node.py
pyfx/view/json_lib/json_widget.py
python_fx-0.3.2.dist-info/LICENSE.txt
python_fx-0.3.2.dist-info/METADATA
python_fx-0.3.2.dist-info/WHEEL
python_fx-0.3.2.dist-info/entry_points.txt
python_fx-0.3.2.dist-info/top_level.txt
python_fx-0.3.2.dist-info/RECORD
