Metadata-Version: 2.1
Name: python-fx
Version: 0.3.2
Summary: A python-native fx-alike terminal JSON viewer.
Author-email: Yutian Wu <yutianwu@umich.edu>
License: MIT
Project-URL: repository, https://github.com/cielong/pyfx
Keywords: fx,pyfx,json viewer,tui
Classifier: Development Status :: 4 - Beta
Classifier: Programming Language :: Python :: 3 :: Only
Classifier: Environment :: Console
Classifier: Operating System :: POSIX
Classifier: Operating System :: MacOS :: MacOS X
Classifier: License :: OSI Approved :: MIT License
Classifier: Topic :: Utilities
Requires-Python: >=3.8
License-File: LICENSE.txt
Requires-Dist: antlr4-python3-runtime==4.13.2
Requires-Dist: first==2.0.2
Requires-Dist: jsonpath-ng==1.6.1
Requires-Dist: ply==3.11
Requires-Dist: pyperclip==1.9.0
Requires-Dist: wcwidth==0.2.13
Requires-Dist: loguru==0.7.2; python_version >= "3.5"
Requires-Dist: dacite==1.8.1; python_version >= "3.6"
Requires-Dist: overrides==7.7.0; python_version >= "3.6"
Requires-Dist: click==8.1.7; python_version >= "3.7"
Requires-Dist: asciimatics==1.15.0; python_version >= "3.8"
Requires-Dist: pillow==10.4.0; python_version >= "3.8"
Requires-Dist: pyyaml==6.0.2; python_version >= "3.8"
Requires-Dist: typing-extensions==4.12.2; python_version >= "3.8"
Requires-Dist: urwid==2.6.15; python_version >= "3.8"
Requires-Dist: yamale==5.2.1; python_version >= "3.8"
Requires-Dist: pyfiglet==1.0.2; python_version >= "3.9"
